dp/__init__.py
dp/_dp_array.py
dp/_index_converter.py
dp/_key_listener.js
dp/_logger.py
dp/_verify.py
dp/_visualizer.py
dp/assets/table.css
dpvis-0.1.0.dist-info/LICENSE
dpvis-0.1.0.dist-info/METADATA
dpvis-0.1.0.dist-info/WHEEL
dpvis-0.1.0.dist-info/RECORD
