Metadata-Version: 2.1
Name: dpvis
Version: 0.1.0
Summary: 
Home-page: https://github.com/itsdawei/dpvis
License: MIT
Author: itsdawei
Author-email: dhlee@usc.edu
Requires-Python: >=3.9,<4.0
Classifier: License :: OSI Approved :: MIT License
Classifier: Programming Language :: Python :: 3
Classifier: Programming Language :: Python :: 3.9
Classifier: Programming Language :: Python :: 3.10
Classifier: Programming Language :: Python :: 3.11
Requires-Dist: colorama (>=0.4.6,<0.5.0)
Requires-Dist: dash (>=2.14.0,<3.0.0)
Requires-Dist: dash-bootstrap-components (>=1.5.0,<2.0.0)
Requires-Dist: fire (>=0.5.0,<0.6.0)
Requires-Dist: numpy (>=1.26,<2.0)
Requires-Dist: plotly (>=5.17.0,<6.0.0)
Project-URL: Repository, https://github.com/itsdawei/dpvis
